{"id":656,"created_at":"2023-10-18 12:17:08.805668+00","exercise_group_id":15,"name":"WORK 2021","slug":"work-2021","value_type_id":3,"user_id":null,"description":"FROM MINUTES 12-20, COMPLETE AS MANY REPS AS POSSIBLE OF:\\nTRACK 1:\\n30 double-unders\\n8 single-arm dumbbell push presses (left arm), ♀35 lb./♂50 lb.\\n8 single-arm dumbbell push presses (right arm), ♀35 lb./♂50 lb.\\n8 lateral burpees over the dumbbell\\n\\nTRACK 2:\\n20 double-unders\\n6 single-arm dumbbell push presses (left arm), ♀35 lb./♂50 lb.\\n6 single-arm dumbbell push presses (right arm), ♀35 lb./♂50 lb.\\n6 burpees\\n\\nTRACK 3:\\n20 single-unders\\n5 single-arm dumbbell push presses (left arm), ♀20 lb./♂35 lb.\\n5 single-arm dumbbell push presses (right arm), ♀20 lb./♂35 lb.\\n5 burpees\\n\\nFor full details on adaptive divisions, visit: https://crossfit.leaderboards.com/competitions/2021-crossfit-lift-move-work/workouts/PVCFHT","sugarword_id":"cty8V2S8m5","subtype_name":null,"coach_notes":null,"athletes_notes":null,"movement_ids":["c94XVoGakB","aFBc9gedzu","h9vPo5JYw6","FrQGIrNfi8"],"updated_at":"2023-11-29 10:30:04.548964+00"}